impath/__init__.py
impath/mask_generation.py
impath-0.1.0.dist-info/METADATA
impath-0.1.0.dist-info/WHEEL
impath-0.1.0.dist-info/top_level.txt
impath-0.1.0.dist-info/RECORD
