Metadata-Version: 2.1
Name: impath
Version: 0.1.0
Summary: Pathology Imaging Tools
Home-page: https://github.com/innovationcore/path_tools_lib
Author: Mitchell Klusty
Author-email: mitchell.klusty@uky.edu
Classifier: Programming Language :: Python :: 3
Classifier: License :: OSI Approved :: MIT License
Classifier: Operating System :: OS Independent
Requires-Python: >=3.7
Requires-Dist: opencv-python>=4.5.0
Requires-Dist: numpy>=1.21.0
Requires-Dist: requests>=2.26.0
Requires-Dist: pillow>=8.0.0
